daculous/__init__.py
daculous-0.0.1.dist-info/WHEEL
daculous-0.0.1.dist-info/METADATA
daculous-0.0.1.dist-info/RECORD
